{
  "basics": {
    "name": "Your Name",
    "label": "Full Stack Developer",
    "email": "you@example.com",
    "phone": "(555) 123-4567",
    "url": "https://yoursite.com",
    "summary": "Full stack developer with 5+ years of experience building web applications. Passionate about developer tooling, TypeScript, and creating products that solve real problems.",
    "location": {
      "city": "San Francisco",
      "region": "CA",
      "countryCode": "US"
    },
    "profiles": [
      {
        "network": "GitHub",
        "username": "yourusername",
        "url": "https://github.com/yourusername"
      },
      {
        "network": "LinkedIn",
        "username": "yourname",
        "url": "https://linkedin.com/in/yourname"
      }
    ]
  },
  "work": [
    {
      "name": "Current Company",
      "position": "Senior Software Engineer",
      "url": "https://company.com",
      "startDate": "2022-01",
      "summary": "Leading development of internal developer tools and customer-facing features.",
      "highlights": [
        "Built real-time collaboration features using WebSockets, reducing sync latency by 60%",
        "Designed and implemented REST API serving 10M+ requests/day",
        "Mentored team of 3 junior developers"
      ]
    },
    {
      "name": "Previous Startup",
      "position": "Software Engineer",
      "startDate": "2019-06",
      "endDate": "2021-12",
      "summary": "Early engineer at a B2B SaaS startup.",
      "highlights": [
        "Shipped core product features used by 500+ enterprise customers",
        "Reduced page load time by 40% through performance optimization",
        "Built CI/CD pipeline reducing deploy time from 30min to 5min"
      ]
    }
  ],
  "education": [
    {
      "institution": "University Name",
      "area": "Computer Science",
      "studyType": "Bachelor of Science",
      "startDate": "2015-09",
      "endDate": "2019-05"
    }
  ],
  "skills": [
    {
      "name": "Languages",
      "keywords": ["TypeScript", "JavaScript", "Python", "SQL"]
    },
    {
      "name": "Frontend",
      "keywords": ["React", "Next.js", "Tailwind CSS", "HTML/CSS"]
    },
    {
      "name": "Backend",
      "keywords": ["Node.js", "PostgreSQL", "Redis", "REST APIs"]
    },
    {
      "name": "Tools",
      "keywords": ["Git", "Docker", "AWS", "Cloudflare Workers"]
    }
  ],
  "projects": [
    {
      "name": "Open Source Project",
      "description": "A developer tool that does something useful",
      "highlights": [
        "500+ GitHub stars",
        "Used by developers at major tech companies"
      ],
      "keywords": ["TypeScript", "CLI", "Developer Tools"],
      "url": "https://github.com/you/project"
    }
  ]
}
